corefuncs/__init__.py
corefuncs/core/__init__.py
corefuncs/core/advanced/__init__.py
corefuncs/core/analysis/__init__.py
corefuncs/core/base/__init__.py
corefuncs/core/database/__init__.py
corefuncs/core/draw/__init__.py
corefuncs-1.1.dist-info/METADATA
corefuncs-1.1.dist-info/WHEEL
corefuncs-1.1.dist-info/top_level.txt
corefuncs-1.1.dist-info/RECORD
