Metadata-Version: 2.1
Name: corefuncs
Version: 1.1
Summary: magic
Author: He Ma
Author-email: 1692303843@qq.com
